{
  "meta": {
    "module": "src.coral.frontier",
    "source": "src/coral/frontier.zig",
    "language": "zig"
  },
  "capabilities": ["coral-ingestion", "coral-database", "coral-mcp", "coral-cache"],
  "used_by": ["src/coral/cache.zig"],
  "members": [
    {
      "type": "struct",
      "name": "MinimizedContext",
      "match_hash": "b5d2d05155a4042e3f64ad24e42ac419f5c1f5e38ef8a75268a80bc5b782b9e1",
      "signature": "keyword_struct MinimizedContext { ... }",
      "is_pub": true,
      "members": [
        {
          "type": "fn_decl",
          "name": "deinit",
          "match_hash": "b180d10dbb7a830417871bebdc081e4537c3c3691966390c41348af40b746225",
          "signature": "fn deinit(self: *MinimizedContext) -> void",
          "params": [
            { "name": "self", "type": "*MinimizedContext" }
          ],
          "returns": "void",
          "is_pub": true,
          "line": 37
        }
      ],
      "line": 27
    },
    {
      "type": "fn_decl",
      "name": "minimizeContext",
      "match_hash": "d3612f78e4ada4e2adacb5302083cca2ea8f590e7a42e71268de2bb0550a27c7",
      "signature": "fn minimizeContext(allocator: std.mem.Allocator, library: *coral_db.Library, query: []const u8, focal_id: i64, token_budget: usize) -> MinimizedContext",
      "params": [
        { "name": "allocator", "type": "std.mem.Allocator" },
        { "name": "library", "type": "*coral_db.Library" },
        { "name": "query", "type": "[]const u8" },
        { "name": "focal_id", "type": "i64" },
        { "name": "token_budget", "type": "usize" }
      ],
      "returns": "MinimizedContext",
      "is_pub": true,
      "line": 48
    },
    {
      "type": "fn_decl",
      "name": "buildPrompt",
      "match_hash": "9ec359327a100852d98626f1ab1c2869117cae64575f4832317ee6b187db22a8",
      "signature": "fn buildPrompt(allocator: std.mem.Allocator, ctx: MinimizedContext) -> []const u8",
      "params": [
        { "name": "allocator", "type": "std.mem.Allocator" },
        { "name": "ctx", "type": "MinimizedContext" }
      ],
      "returns": "[]const u8",
      "is_pub": true,
      "line": 92
    },
    {
      "type": "fn_decl",
      "name": "validateSolution",
      "match_hash": "9ac003cf747af09298bf0e78b6c3b7f00eb3fe8406aa2d728c080997a0808689",
      "signature": "fn validateSolution(solution: []const u8) -> ValidationResult",
      "params": [
        { "name": "solution", "type": "[]const u8" }
      ],
      "returns": "ValidationResult",
      "is_pub": true,
      "line": 120
    },
    {
      "type": "test_decl",
      "name": "validateSolution: empty returns invalid",
      "is_pub": false,
      "line": 148
    },
    {
      "type": "test_decl",
      "name": "validateSolution: refusal returns invalid",
      "is_pub": false,
      "line": 153
    },
    {
      "type": "test_decl",
      "name": "validateSolution: think block returns invalid",
      "is_pub": false,
      "line": 158
    },
    {
      "type": "test_decl",
      "name": "validateSolution: valid prose returns valid",
      "is_pub": false,
      "line": 163
    },
    {
      "type": "test_decl",
      "name": "buildPrompt: contains query and context",
      "is_pub": false,
      "line": 168
    },
    {
      "type": "fn_decl",
      "name": "indexSolution",
      "match_hash": "60f7206da0827e91d3cb29b81d874a635ee6105236341c4fd82a368c14c01902",
      "signature": "fn indexSolution(allocator: std.mem.Allocator, library: *coral_db.Library, query: []const u8, response: []const u8) -> void",
      "params": [
        { "name": "allocator", "type": "std.mem.Allocator" },
        { "name": "library", "type": "*coral_db.Library" },
        { "name": "query", "type": "[]const u8" },
        { "name": "response", "type": "[]const u8" }
      ],
      "returns": "void",
      "is_pub": true,
      "line": 205
    },
    {
      "type": "test_decl",
      "name": "indexSolution: smoke test with in-memory library",
      "is_pub": false,
      "line": 255
    },
    {
      "type": "test_decl",
      "name": "indexSolution: idempotent on repeated call",
      "is_pub": false,
      "line": 265
    },
    {
      "type": "fn_decl",
      "name": "indexSolutionWithTool",
      "match_hash": "67e6bc67baac4dd582d098c9eb620b6b40529cf09bb0c719afe3e3f3ed279fbe",
      "signature": "fn indexSolutionWithTool(allocator: std.mem.Allocator, library: *coral_db.Library, query: []const u8, response: []const u8, generator: ?*wasm_mod.ToolGenerator) -> void",
      "params": [
        { "name": "allocator", "type": "std.mem.Allocator" },
        { "name": "library", "type": "*coral_db.Library" },
        { "name": "query", "type": "[]const u8" },
        { "name": "response", "type": "[]const u8" },
        { "name": "generator", "type": "?*wasm_mod.ToolGenerator" }
      ],
      "returns": "void",
      "is_pub": true,
      "line": 298
    },
    {
      "type": "test_decl",
      "name": "indexSolutionWithTool: null generator falls back to ContextNode indexing",
      "is_pub": false,
      "line": 360
    },
    {
      "type": "test_decl",
      "name": "indexSolutionWithTool: no code block still indexes node",
      "is_pub": false,
      "line": 377
    }
  ]
}
