{
  "meta": {
    "module": "src.guidance.codebase_map",
    "source": "src/guidance/codebase_map.zig",
    "language": "zig"
  },
  "comment": " codebase_map.zig — Structural discovery layer for `guidance explain`.\n\n Implements M3 of ROADMAP_20260403_FLUENT_GUIDANCE.md:\n Build a language-agnostic map of the codebase from README.md, STRUCTURE.md,\n filesystem walk, and entry point detection.\n\n This module is stateless (pure functions) except for CodebaseMap which owns\n its strings. Call deinit() to release.",
  "used_by": ["src/guidance/infer_capabilities.zig", "src/guidance/ralph.zig", "src/guidance/scanner.zig"],
  "members": [
    {
      "type": "enum",
      "name": "BuildSystem",
      "match_hash": "19e4d80da29ad8679d50123e05b08b89eae8d845600d8f2c8fce2d2de9770597",
      "signature": "keyword_enum BuildSystem { ... }",
      "is_pub": true,
      "members": [
        {
          "type": "enum_field",
          "name": "zig_build",
          "is_pub": false,
          "line": 18
        }
    ,    {
          "type": "enum_field",
          "name": "make",
          "is_pub": false,
          "line": 19
        }
    ,    {
          "type": "enum_field",
          "name": "cargo",
          "is_pub": false,
          "line": 20
        }
    ,    {
          "type": "enum_field",
          "name": "npm",
          "is_pub": false,
          "line": 21
        }
    ,    {
          "type": "enum_field",
          "name": "gradle",
          "is_pub": false,
          "line": 22
        }
    ,    {
          "type": "enum_field",
          "name": "cmake",
          "is_pub": false,
          "line": 23
        }
    ,    {
          "type": "enum_field",
          "name": "poetry",
          "is_pub": false,
          "line": 24
        }
    ,    {
          "type": "enum_field",
          "name": "unknown",
          "is_pub": false,
          "line": 25
        }
    ,    {
          "type": "fn_decl",
          "name": "buildCommand",
          "match_hash": "bef4d01ad547913e2260d7120c59d1f3e242e65cc2f38e0e75e6edc0ca0bc96a",
          "signature": "fn buildCommand(self: BuildSystem) -> []const u8",
          "params": [
            { "name": "self", "type": "BuildSystem" }
          ],
          "returns": "[]const u8",
          "is_pub": true,
          "line": 27
        }
      ],
      "line": 17
    },
    {
      "type": "struct",
      "name": "EntryPoint",
      "match_hash": "88e6cf9624b20eb994643674e088176e0af2f0a7c4f789394f45444e4ff92dd7",
      "signature": "keyword_struct EntryPoint { ... }",
      "is_pub": true,
      "line": 42
    },
    {
      "type": "struct",
      "name": "DirectoryEntry",
      "match_hash": "98ef9beb5f3c304c8342a041f28559ba2c853f4ee8605c4b785b70ee39b3a959",
      "signature": "keyword_struct DirectoryEntry { ... }",
      "is_pub": true,
      "line": 54
    },
    {
      "type": "struct",
      "name": "CodebaseMap",
      "match_hash": "1462ef1d44dfd58738c027b770d905fb259fcc95b3080ec26089078573862e7a",
      "signature": "keyword_struct CodebaseMap { ... }",
      "is_pub": true,
      "members": [
        {
          "type": "fn_decl",
          "name": "deinit",
          "match_hash": "5c8bce72b6f39a4e25a2ea8d70ca5c2c27511085723aa2f30759a9013017a42f",
          "signature": "fn deinit(self: *CodebaseMap) -> void",
          "params": [
            { "name": "self", "type": "*CodebaseMap" }
          ],
          "returns": "void",
          "is_pub": true,
          "line": 93
        }
      ],
      "line": 69
    },
    {
      "type": "fn_decl",
      "name": "discoverStructure",
      "match_hash": "44a0fde08a51e503017ed01ba078664d864629279bb8feb8301e3f604f457ad0",
      "signature": "fn discoverStructure(allocator: std.mem.Allocator, workspace: []const u8) -> CodebaseMap",
      "params": [
        { "name": "allocator", "type": "std.mem.Allocator" },
        { "name": "workspace", "type": "[]const u8" }
      ],
      "returns": "CodebaseMap",
      "is_pub": true,
      "line": 126
    },
    {
      "type": "fn_private",
      "name": "detectBuildSystem",
      "match_hash": "191735ae1a230e45f66020591db17b83e25b1dc0241f0b66f48988bc46f48193",
      "signature": "fn detectBuildSystem(workspace: []const u8) -> BuildSystem",
      "params": [
        { "name": "workspace", "type": "[]const u8" }
      ],
      "returns": "BuildSystem",
      "is_pub": false,
      "line": 189
    },
    {
      "type": "fn_private",
      "name": "shouldIgnoreDir",
      "match_hash": "d625f8f3758fcf74ac14e016f2530028662f5b09842f7e06a748a455d89c57f4",
      "signature": "fn shouldIgnoreDir(name: []const u8) -> bool",
      "params": [
        { "name": "name", "type": "[]const u8" }
      ],
      "returns": "bool",
      "is_pub": false,
      "line": 216
    },
    {
      "type": "fn_private",
      "name": "walkFilesystem",
      "match_hash": "252196a2551ba51a324900c6a45b43e114fcbf079b8d30b2682fcebafd543664",
      "signature": "fn walkFilesystem(allocator: std.mem.Allocator, workspace: []const u8, tree: *std.ArrayList(DirectoryEntry)) -> void",
      "params": [
        { "name": "allocator", "type": "std.mem.Allocator" },
        { "name": "workspace", "type": "[]const u8" },
        { "name": "tree", "type": "*std.ArrayList(DirectoryEntry)" }
      ],
      "returns": "void",
      "is_pub": false,
      "line": 228
    },
    {
      "type": "fn_private",
      "name": "walkDir",
      "match_hash": "7978ba689bca3d1aebb9b82a23cc914a0afdb007b8c20172c8277bb1edcbee7e",
      "signature": "fn walkDir(allocator: std.mem.Allocator, dir: std.fs.Dir, rel_prefix: []const u8, tree: *std.ArrayList(DirectoryEntry), depth: u32) -> void",
      "params": [
        { "name": "allocator", "type": "std.mem.Allocator" },
        { "name": "dir", "type": "std.fs.Dir" },
        { "name": "rel_prefix", "type": "[]const u8" },
        { "name": "tree", "type": "*std.ArrayList(DirectoryEntry)" },
        { "name": "depth", "type": "u32" }
      ],
      "returns": "void",
      "is_pub": false,
      "line": 239
    },
    {
      "type": "fn_private",
      "name": "countLanguages",
      "match_hash": "0fa6f89863d0a241d07e5f00c91b581a5a7f72656b8d5ceec734b0ea9ad0f5e9",
      "signature": "fn countLanguages(allocator: std.mem.Allocator, tree: []const DirectoryEntry) -> []LanguageCount",
      "params": [
        { "name": "allocator", "type": "std.mem.Allocator" },
        { "name": "tree", "type": "[]const DirectoryEntry" }
      ],
      "returns": "[]LanguageCount",
      "is_pub": false,
      "line": 293
    },
    {
      "type": "fn_private",
      "name": "classifyEntryPoint",
      "match_hash": "56133862fde9aee6b43f8ff603ade3c40e02dc87b8182ec0a47efeb6eec7741b",
      "signature": "fn classifyEntryPoint(name: []const u8) -> @TypeOf(@as(EntryPoint, undefined).kind)",
      "params": [
        { "name": "name", "type": "[]const u8" }
      ],
      "returns": "@TypeOf(@as(EntryPoint, undefined).kind)",
      "is_pub": false,
      "line": 348
    },
    {
      "type": "fn_private",
      "name": "isEntryPointName",
      "match_hash": "386b2b04d46f478432b46fc47c7194e99432a0eb996b1a83b2362b8db9cac7c9",
      "signature": "fn isEntryPointName(name: []const u8) -> bool",
      "params": [
        { "name": "name", "type": "[]const u8" }
      ],
      "returns": "bool",
      "is_pub": false,
      "line": 359
    },
    {
      "type": "fn_private",
      "name": "detectEntryPoints",
      "match_hash": "8c0187a6cf42432d52fdf97f52d8eeb0a1d93701696390117cdc6a821bbc05b4",
      "signature": "fn detectEntryPoints(allocator: std.mem.Allocator, tree: []const DirectoryEntry, workspace: []const u8) -> []EntryPoint",
      "params": [
        { "name": "allocator", "type": "std.mem.Allocator" },
        { "name": "tree", "type": "[]const DirectoryEntry" },
        { "name": "workspace", "type": "[]const u8" }
      ],
      "returns": "[]EntryPoint",
      "is_pub": false,
      "line": 373
    },
    {
      "type": "fn_private",
      "name": "findCapabilityDirs",
      "match_hash": "9659a7d998233056408ea92ec38262f0938be9e5ee3eb82013a91c9a6e27fe19",
      "signature": "fn findCapabilityDirs(allocator: std.mem.Allocator, workspace: []const u8, tree: []const DirectoryEntry) -> [][]const u8",
      "params": [
        { "name": "allocator", "type": "std.mem.Allocator" },
        { "name": "workspace", "type": "[]const u8" },
        { "name": "tree", "type": "[]const DirectoryEntry" }
      ],
      "returns": "[][]const u8",
      "is_pub": false,
      "line": 449
    },
    {
      "type": "fn_private",
      "name": "findSkillDirs",
      "match_hash": "910d6a5716495ddb197815f883a0cea9fbc6aeb6e0be820b22c52912fd154106",
      "signature": "fn findSkillDirs(allocator: std.mem.Allocator, workspace: []const u8, tree: []const DirectoryEntry) -> [][]const u8",
      "params": [
        { "name": "allocator", "type": "std.mem.Allocator" },
        { "name": "workspace", "type": "[]const u8" },
        { "name": "tree", "type": "[]const DirectoryEntry" }
      ],
      "returns": "[][]const u8",
      "is_pub": false,
      "line": 490
    },
    {
      "type": "fn_private",
      "name": "extractReadmeDescription",
      "match_hash": "7a292c6ebc2b6861bb5452c608fd12bec248efbb94253dde347f2e35a169b567",
      "signature": "fn extractReadmeDescription(allocator: std.mem.Allocator, workspace: []const u8) -> []const u8",
      "params": [
        { "name": "allocator", "type": "std.mem.Allocator" },
        { "name": "workspace", "type": "[]const u8" }
      ],
      "returns": "[]const u8",
      "is_pub": false,
      "line": 517
    },
    {
      "type": "test_decl",
      "name": "detectBuildSystem: returns zig_build for this repo",
      "is_pub": false,
      "line": 566
    },
    {
      "type": "test_decl",
      "name": "looksLikeIdentifier via ENTRY_EXACT: main is an entry point",
      "is_pub": false,
      "line": 574
    }
  ]
}
