{
  "meta": {
    "module": "src.guidance.stage_builder",
    "source": "src/guidance/stage_builder.zig",
    "language": "zig"
  },
  "comment": "[gof-patterns]  stage_builder.zig — Stage builder for typed, pre-allocated stage production.\n\n Anti-pattern fixed: VTable had exactly one implementation.\n Replaced with direct struct methods on GuidanceJsonStageBuilderImpl.",
  "skills": [
    { "ref": "skills/gof-patterns/SKILL.md", "context": "GoF patterns detected" }
  ],
  "used_by": ["src/guidance/stage_builder_tests.zig"],
  "members": [
    {
      "type": "struct",
      "name": "GuidanceJsonStageBuilderImpl",
      "match_hash": "e53782cfb63919d16806e89966e5b08165adae54bcbb3fdfa7fe95ce871ac059",
      "signature": "keyword_struct GuidanceJsonStageBuilderImpl { ... }",
      "is_pub": true,
      "members": [
        {
          "type": "fn_decl",
          "name": "init",
          "match_hash": "469a61406b223bb778f05e406e212f72287cb2c612a92cbc9a6920532215afa7",
          "signature": "fn init(allocator: std.mem.Allocator, doc: *const types.GuidanceDoc, workspace: []const u8) -> GuidanceJsonStageBuilderImpl",
          "returns": "GuidanceJsonStageBuilderImpl",
          "is_pub": true,
          "line": 18
        },
        {
          "type": "fn_decl",
          "name": "stageCount",
          "match_hash": "95329986b7cb1872fe28495feee6d89d42d0e1c6d2054a8720aa787038f0fdc1",
          "signature": "fn stageCount(self: *const GuidanceJsonStageBuilderImpl) -> usize",
          "returns": "usize",
          "is_pub": true,
          "line": 22
        },
        {
          "type": "fn_decl",
          "name": "fillStages",
          "match_hash": "dccf1d898822ee71fb4d65dfe200688c396e7fe8f92cb3d6f970827635b90fa3",
          "signature": "fn fillStages(self: *GuidanceJsonStageBuilderImpl, alloc: std.mem.Allocator, out: []types.Stage) -> usize",
          "returns": "usize",
          "is_pub": true,
          "line": 31
        },
        {
          "type": "fn_decl",
          "name": "isRelevant",
          "match_hash": "f7caf48234057ba0458396b3d3adf1c7d634820016481c689c5c784294047f03",
          "signature": "fn isRelevant(self: *const GuidanceJsonStageBuilderImpl, query_tokens: []const []const u8) -> bool",
          "returns": "bool",
          "is_pub": true,
          "line": 93
        },
        {
          "type": "fn_decl",
          "name": "buildStages",
          "match_hash": "bc419bc6aae30ab0ff1fcbcac73fd0c8bf3535d9aa319eeddbf0cfb197db5abe",
          "signature": "fn buildStages(self: *GuidanceJsonStageBuilderImpl, allocator: std.mem.Allocator) -> []types.Stage",
          "returns": "[]types.Stage",
          "is_pub": true,
          "line": 106
        },
        {
          "type": "fn_decl",
          "name": "deinit",
          "match_hash": "18f7e2ccce55d0e816fde4ef3e7a7d2fe0bcce53a316c0ce7b3eb26b18628788",
          "signature": "fn deinit(self: *GuidanceJsonStageBuilderImpl) -> void",
          "returns": "void",
          "is_pub": true,
          "line": 114
        }
      ],
      "line": 13
    },
    {
      "type": "fn_decl",
      "name": "createStageBuilder",
      "match_hash": "436d4c491623029d95a8f8bb8dffa4b61a8ad2a028637393d147ccf641182e4d",
      "signature": "fn createStageBuilder(allocator: std.mem.Allocator, doc: *const types.GuidanceDoc, workspace: []const u8) -> *GuidanceJsonStageBuilderImpl",
      "returns": "*GuidanceJsonStageBuilderImpl",
      "patterns": [
        { "name": "Factory (GoF)", "type": "GoF", "ref": "guidance/skills/gof-patterns/SKILL.md#factory" }
      ],
      "is_pub": true,
      "line": 119
    },
    {
      "type": "fn_decl",
      "name": "collectRelevantStages",
      "match_hash": "fc16c5fc27fa37937e39a47f222f94251ba1efa8d603bc8e24f2a96fad8fd326",
      "signature": "fn collectRelevantStages(allocator: std.mem.Allocator, builders: []const *GuidanceJsonStageBuilderImpl, query_tokens: []const []const u8, max_stages: usize) -> []types.Stage",
      "returns": "[]types.Stage",
      "is_pub": true,
      "line": 129
    },
    {
      "type": "test_decl",
      "name": "GuidanceJsonStageBuilder: stageCount returns non-zero for doc with detail",
      "is_pub": false,
      "line": 166
    },
    {
      "type": "test_decl",
      "name": "GuidanceJsonStageBuilder: buildStages produces prose stage from detail",
      "is_pub": false,
      "line": 179
    },
    {
      "type": "test_decl",
      "name": "GuidanceJsonStageBuilder: isRelevant matches source path token",
      "is_pub": false,
      "line": 199
    }
  ]
}
