{
  "meta": {
    "module": "src.vector.math",
    "source": "src/vector/math.zig",
    "language": "zig"
  },
  "comment": " Vector operations — cosine similarity, normalization, hybrid merge.\n\n Used by guidance's SQLite vector search backend.",
  "keywords": ["Vector operations", "cosine similarity", "normalization", "hybrid merge", "AI coding assistant", "LanceDB", "serialization", "deserialization", "vector search", "numerical stability"],
  "capabilities": ["vector-search"],
  "used_by": ["src/vector/root.zig"],
  "members": [
    {
      "type": "fn_decl",
      "name": "cosineSimilarity",
      "match_hash": "715718c5ba0399b40e9e044a54670eb2cd6774f2e174fc79aee93cb3c998303f",
      "signature": "fn cosineSimilarity(a: []const f32, b: []const f32) -> f32",
      "params": [
        { "name": "a", "type": "[]const f32" },
        { "name": "b", "type": "[]const f32" }
      ],
      "returns": "f32",
      "is_pub": true,
      "line": 10
    },
    {
      "type": "fn_decl",
      "name": "vecToBytes",
      "match_hash": "a6658a0730ae2b5f1298697aa8bdb85850a302e875de6fd1c495cb30371699dc",
      "signature": "fn vecToBytes(allocator: std.mem.Allocator, v: []const f32) -> []u8",
      "params": [
        { "name": "allocator", "type": "std.mem.Allocator" },
        { "name": "v", "type": "[]const f32" }
      ],
      "returns": "[]u8",
      "is_pub": true,
      "line": 43
    },
    {
      "type": "fn_decl",
      "name": "bytesToVec",
      "match_hash": "4503a1dffc11e7bee7574d409534eddb53778063f9c8ed2829164562ca9e8e37",
      "signature": "fn bytesToVec(allocator: std.mem.Allocator, bytes: []const u8) -> []f32",
      "params": [
        { "name": "allocator", "type": "std.mem.Allocator" },
        { "name": "bytes", "type": "[]const u8" }
      ],
      "returns": "[]f32",
      "is_pub": true,
      "line": 53
    },
    {
      "type": "struct",
      "name": "ScoredResult",
      "match_hash": "02335e342defc548fe5128293a421398514c3b4e665cf1855a1dbd68e8d33e59",
      "signature": "keyword_struct ScoredResult { ... }",
      "is_pub": true,
      "line": 66
    },
    {
      "type": "fn_decl",
      "name": "hybridMerge",
      "match_hash": "ab56980c41aea4f340187cb28570d5749c5f759c06e862f29d03fbbfc0831636",
      "signature": "fn hybridMerge(allocator: std.mem.Allocator, vector_results: []const IdScore, keyword_results: []const IdScore, vector_weight: f32, keyword_weight: f32, limit: usize) -> []ScoredResult",
      "params": [
        { "name": "allocator", "type": "std.mem.Allocator" },
        { "name": "vector_results", "type": "[]const IdScore" },
        { "name": "keyword_results", "type": "[]const IdScore" },
        { "name": "vector_weight", "type": "f32" },
        { "name": "keyword_weight", "type": "f32" },
        { "name": "limit", "type": "usize" }
      ],
      "returns": "[]ScoredResult",
      "is_pub": true,
      "line": 87
    },
    {
      "type": "fn_decl",
      "name": "hybridMergeThree",
      "match_hash": "5cfa4f88ecceb34a0a6ebeed12c76e80e62cd10f0b8d68174c3145a4f62ff087",
      "signature": "fn hybridMergeThree(allocator: std.mem.Allocator, vector_results: []const IdScore, keyword_results: []const IdScore, capability_results: []const IdScore, cosine_w: f32, keyword_w: f32, cap_w: f32, limit: usize) -> []ScoredResult",
      "params": [
        { "name": "allocator", "type": "std.mem.Allocator" },
        { "name": "vector_results", "type": "[]const IdScore" },
        { "name": "keyword_results", "type": "[]const IdScore" },
        { "name": "capability_results", "type": "[]const IdScore" },
        { "name": "cosine_w", "type": "f32" },
        { "name": "keyword_w", "type": "f32" },
        { "name": "cap_w", "type": "f32" },
        { "name": "limit", "type": "usize" }
      ],
      "returns": "[]ScoredResult",
      "is_pub": true,
      "line": 168
    },
    {
      "type": "test_decl",
      "name": "cosine identical vectors",
      "is_pub": false,
      "line": 270
    },
    {
      "type": "test_decl",
      "name": "cosine orthogonal vectors",
      "is_pub": false,
      "line": 276
    },
    {
      "type": "test_decl",
      "name": "cosine empty returns zero",
      "is_pub": false,
      "line": 283
    },
    {
      "type": "test_decl",
      "name": "vec bytes roundtrip",
      "is_pub": false,
      "line": 288
    },
    {
      "type": "test_decl",
      "name": "hybrid merge deduplicates",
      "is_pub": false,
      "line": 302
    },
    {
      "type": "test_decl",
      "name": "hybrid merge respects limit",
      "is_pub": false,
      "line": 314
    },
    {
      "type": "test_decl",
      "name": "hybrid merge three-way combines all scores",
      "is_pub": false,
      "line": 324
    }
  ]
}
